hahaha_utils/__init__.py
hahaha_utils/aes_encrypt.py
hahaha_utils/ascii_font.py
hahaha_utils/baidu_ocr.py
hahaha_utils/canal_client.py
hahaha_utils/config_inte.py
hahaha_utils/config_loca.py
hahaha_utils/config_prod.py
hahaha_utils/config_test.py
hahaha_utils/convert_pdf_table_html.py
hahaha_utils/copy_text.py
hahaha_utils/csv_to_excel.py
hahaha_utils/download_active_code.py
hahaha_utils/es_client.py
hahaha_utils/file_handler.py
hahaha_utils/get_pip.py
hahaha_utils/header_pretty.py
hahaha_utils/image_handler.py
hahaha_utils/kafka_consumer.py
hahaha_utils/kafka_producter.py
hahaha_utils/log_handler.py
hahaha_utils/mail_date_list.py
hahaha_utils/mongo_client.py
hahaha_utils/mysql_client.py
hahaha_utils/parse_sql.py
hahaha_utils/pdf_to_picture.py
hahaha_utils/py3_connect_ssh.py
hahaha_utils/python_cmd_with_admin.py
hahaha_utils/python_command.py
hahaha_utils/rabbit_mq_consumer.py
hahaha_utils/rabbit_mq_exchange_consumer.py
hahaha_utils/rabbit_mq_exchange_producter.py
hahaha_utils/rabbit_mq_producer.py
hahaha_utils/receive_mail.py
hahaha_utils/send_mail.py
hahaha_utils/web_parse.py
hahaha_utils/web_request.py
hahaha_utils-1.1.2.dist-info/LICENSE
hahaha_utils-1.1.2.dist-info/METADATA
hahaha_utils-1.1.2.dist-info/WHEEL
hahaha_utils-1.1.2.dist-info/top_level.txt
hahaha_utils-1.1.2.dist-info/RECORD
