Metadata-Version: 2.1
Name: hahaha-utils
Version: 1.1.2
Summary: HAHAHA Python3 Utils
Home-page: https://www.idannywu.com
Author: Danny
Author-email: mrdanny1024@gmail.com
License: MIT
Classifier: License :: OSI Approved :: MIT License
Classifier: Programming Language :: Python :: 3
Classifier: Programming Language :: Python :: 3.5
Classifier: Programming Language :: Python :: 3.6
Classifier: Programming Language :: Python :: 3.7
Classifier: Programming Language :: Python :: 3.8
Classifier: Programming Language :: Python :: 3.9
Classifier: Programming Language :: Python :: 3.10
Classifier: Programming Language :: Python :: 3.11
Classifier: Programming Language :: Python :: Implementation :: CPython
Classifier: Programming Language :: Python :: Implementation :: PyPy
Requires-Python: >=2.7, !=3.0.*, !=3.1.*, !=3.2.*, !=3.3.*, !=3.4.*
License-File: LICENSE
Requires-Dist: pika
Requires-Dist: pandas
Requires-Dist: matplotlib
Requires-Dist: colorama
Requires-Dist: yagmail
Requires-Dist: termcolor
Requires-Dist: camelot-py
Requires-Dist: requests
Requires-Dist: kafka-python
Requires-Dist: pyperclip
Requires-Dist: lxml
Requires-Dist: fitz
Requires-Dist: baidu-aip
Requires-Dist: scipy
Requires-Dist: PyMySQL
Requires-Dist: pyfiglet
Requires-Dist: opencv-python
Requires-Dist: numpy
Requires-Dist: wheel
Requires-Dist: paramiko
Requires-Dist: camelot
Requires-Dist: kafka
Requires-Dist: Pillow
Requires-Dist: pip
Requires-Dist: pycryptodome
Requires-Dist: elasticsearch
Requires-Dist: canal-python
